[
  {
    "id": "MEM-100-14",
    "position_title": "Staff Assistant",
    "office": "Senior Democratic member of Congress",
    "location": "District of Columbia",
    "posting_date": "2014-01-06",
    "description": "We are seeking a highly energetic, motivated, and organized individual to join the team of a Senior Democratic member of Congress. The candidate will have strong interpersonal skills, be comfortable with managing multiple tasks and work well under pressure.\n\nThe staff assistant is responsible for preparing letters of greetings, condolence and congratulations on behalf of the Member; answering the phones; coordinating mail and casework distribution; making room reservations for meetings. Light casework assignments will include post office problems and requests for expedited passports and as assigned by the District Director. The staff assistant also serves as intern coordinator by recruiting training, scheduling and assigning duties.",
    "responsibilities": [
      "Preparing letters of greetings, condolence and congratulations on behalf of the Member",
      "Answering the phones",
      "Coordinating mail and casework distribution",
      "Making room reservations for meetings",
      "Light casework assignments will include post office problems and requests for expedited passports and as assigned by the District Director",
      "Serves as intern coordinator by recruiting training, scheduling and assigning duties"
    ],
    "qualifications": [
      "Bachelor’s degree",
      "Significant experience interacting with the public",
      "Excellent writing and communication skills",
      "Working knowledge of the District of Columbia",
      "Candidate must be a resident of the District of Columbia or willing to move immediately to D.C., if hired"
    ],
    "how_to_apply": "Interested applicants should send a resume, cover letter, references and two writing samples to: DC00.NortonResume@mail.houe.gov or fax to (202) 225-1129. Absolutely no phone calls will be accepted!",
    "salary_info": "Salary is based on skill and experience level.",
    "contact": "DC00.NortonResume@mail.houe.gov",
    "equal_opportunity": null,
    "job_category": "administrative"
  },
  {
    "id": "MEM-378-13",
    "position_title": "Legislative Assistant",
    "office": "Texas Democrat",
    "location": null,
    "posting_date": "2014-01-06",
    "description": "Moderate Texas Democrat seeks a Legislative Assistant to handle healthcare, social security, Medicare, education, and other issues. Our office is fast-paced with a proactive group of staffers who place a premium on cooperation and teamwork. A successful candidate is an easy-going, self-starter who will be responsible for: (a) quickly learning district priorities, (b) preparing research / analysis for votes, (c) tracking legislation, (d) providing guidance on issues to the communications director and legislative correspondents, and (e) other duties as assigned. We're looking for a fun, relaxed addition to the team who is very driven to take initiative and also has a willingness to keep learning on the job. Unfortunately, this is not an entry level position. Please submit a cover letter, resume, and writing sample (e.g., one page memo or similar) to TXResume@mail.house.gov. No calls or drop-ins, please.",
    "responsibilities": [
      "quickly learning district priorities",
      "preparing research / analysis for votes",
      "tracking legislation",
      "providing guidance on issues to the communications director and legislative correspondents",
      "other duties as assigned"
    ],
    "qualifications": [],
    "how_to_apply": "Please submit a cover letter, resume, and writing sample (e.g., one page memo or similar) to TXResume@mail.house.gov. No calls or drop-ins, please.",
    "salary_info": null,
    "contact": "TXResume@mail.house.gov",
    "equal_opportunity": null,
    "job_category": "legislative"
  },
  {
    "id": "MEM-376-13",
    "position_title": "Press secretary",
    "office": "Dem member",
    "location": "DC",
    "posting_date": "2014-01-06",
    "description": "Dem member seeks press secretary for DC office, Hill experience a plus, not required.",
    "responsibilities": [],
    "qualifications": [],
    "how_to_apply": "Please submit resumes to DCPRSecCV@gmail.com",
    "salary_info": null,
    "contact": "DCPRSecCV@gmail.com",
    "equal_opportunity": null,
    "job_category": "communications"
  },
  {
    "id": "MEM-375-13",
    "position_title": "Communications Director",
    "office": "Congressman Aaron Schock (IL-18)",
    "location": "District and National",
    "posting_date": "2014-01-06",
    "description": "Congressman Aaron Schock (IL-18) seeks an experienced Communications Director to manage a fast-paced press operation. Strong speech writing skills are a must as duties include: working with the Congressman to help craft talking points, speeches and op-eds; writing press releases and e-newsletters; booking and pitching media outlets nationally and in district; and maintaining and updating the Member’s website. The ideal candidate has demonstrated creative writing and speech writing skills. In addition, the job requires one to be innovative and proactive in growing district and national media opportunities for the Congressman. Must have the ability to work with diverse media outlets, write well under a deadline, and have experience working in communications.",
    "responsibilities": [
      "working with the Congressman to help craft talking points, speeches and op-eds",
      "writing press releases and e-newsletters",
      "booking and pitching media outlets nationally and in district",
      "maintaining and updating the Member’s website"
    ],
    "qualifications": [
      "demonstrated creative writing and speech writing skills",
      "innovative and proactive in growing district and national media opportunities",
      "ability to work with diverse media outlets",
      "ability to write well under a deadline",
      "experience working in communications"
    ],
    "how_to_apply": "Qualified applicants should send resume and writing sample to IL18resumes@gmail.com.",
    "salary_info": null,
    "contact": "IL18resumes@gmail.com",
    "equal_opportunity": null,
    "job_category": "communications"
  },
  {
    "id": "MEM-374-13",
    "position_title": "Legislative Assistant",
    "office": "Freshman Democratic Member",
    "location": "Washington, DC",
    "posting_date": "2014-01-06",
    "description": "Freshman Democratic Member seeks an organized, energetic and savvy Legislative Assistant to handle the Member’s work on the House Financial Services Committee, with a focus on economic development, affordable housing and infrastructure needs of America’s legacy cities. The selected candidate will be joining a fast-paced, team-oriented Washington, DC office.",
    "responsibilities": [
      "Preparing and staffing the Member for committee hearings and markups",
      "Monitoring legislative developments within Committees and on the House floor",
      "Developing and advancing legislation and other policy priorities of the Member",
      "Contributing to floor speeches and other external communications",
      "Researching and advising the Member on bills and other issues",
      "Representing the Member in meetings",
      "Drafting constituent correspondence",
      "This legislative portfolio will also include additional issues outside of the HFSC work."
    ],
    "qualifications": [
      "Applicants must have superior organizational skills, strong written and oral communication skills, and strong interpersonal skills",
      "Be able to multi-task and thrive in a fast paced environment",
      "Have poise, patience and a sense of humor",
      "Prior experience in economic development and community/urban planning strongly preferred",
      "Michigan ties a plus"
    ],
    "how_to_apply": "Please email a resume and cover letter to Michigan05jobs@gmail.com with “Legislative Assistant” in the subject line.",
    "salary_info": null,
    "contact": "Michigan05jobs@gmail.com",
    "equal_opportunity": null,
    "job_category": "legislative"
  },
  {
    "id": "MEM-373-13",
    "position_title": "Press Assistant",
    "office": "Ohio Republican House Member",
    "location": null,
    "posting_date": "2014-01-06",
    "description": "Ohio Republican House Member seeking press assistant to join staff. Applicants should be self-starting, hard-working and creative. Must have strong writing and verbal skills and be extremely detail oriented. Possibility of eventual promotion to press secretary a possibility based on job performance over time.",
    "responsibilities": [
      "managing all new media platforms (Facebook, Twitter, You Tube and Instagram)",
      "updating the web site",
      "writing press releases and columns",
      "creating videos and graphics",
      "taking photos and running telephone town halls"
    ],
    "qualifications": [
      "strong writing and verbal skills",
      "extremely detail oriented",
      "Experience with new media, HTML, Final Cut Pro, Movie Maker and Photoshop helpful."
    ],
    "how_to_apply": "Interested applicants should send cover letter, resume and writing sample to oh.ushouse.job@gmail.com.",
    "salary_info": null,
    "contact": "oh.ushouse.job@gmail.com",
    "equal_opportunity": null,
    "job_category": "communications"
  },
  {
    "id": "MEM-370-13",
    "position_title": "Press Secretary",
    "office": "Senior Republican",
    "location": "DC",
    "posting_date": "2014-01-06",
    "description": "Senior Republican seeking press secretary with superior writing skills who is energetic, creative, strategic, and quick-thinking. The successful candidate is a self-starter who is politically astute and can quickly master a range of issues in time-sensitive situations.",
    "responsibilities": [
      "Drafting/distributing press releases",
      "Writing weekly newsletters, OpEds",
      "Maintaining and updating website content",
      "Preparation of talking points and speeches",
      "Establishing and maintaining strong relations with district and DC media and executing an aggressive earned local media campaign"
    ],
    "qualifications": [
      "New media skills are a must, including knowledge of video, audio and/or photography and editing in those mediums as well as social media"
    ],
    "how_to_apply": "Email resumes to PA.Resumes@mail.house.gov.",
    "salary_info": null,
    "contact": "PA.Resumes@mail.house.gov",
    "equal_opportunity": null,
    "job_category": "communications"
  }
]