[
  {
    "id": "MEM-348-14",
    "position_title": "Social Media Press Assistant",
    "office": "Ohio Democratic Member",
    "location": null,
    "posting_date": "2014-11-03",
    "description": "Ohio Democratic Member seeks a hardworking Social Media Press Assistant to join a busy, proactive team. Applicant must be able to multitask, and thrive while working long hours.",
    "responsibilities": [
      "Developing, writing, and editing content for online platforms including Facebook, Twitter, LinkedIn, YouTube and Instagram",
      "Website development & maintenance",
      "Other duties as assigned"
    ],
    "qualifications": [
      "Applicants must have experience directly managing social media accounts, and a proven record of maintaining a web presence by building, maintaining and engaging active web-based/social media audiences to meet outreach and impact goals."
    ],
    "how_to_apply": "Please send cover letter, resume, and two original writing samples to District11Resumes@mail.house.gov with “SOCIAL MEDIA PRESS ASSISTANT” in the subject line. No walk-ins or phone calls.",
    "salary_info": "Salary is commensurate with experience.",
    "contact": "District11Resumes@mail.house.gov",
    "equal_opportunity": null
  },
  {
    "id": "MEM-347-14",
    "position_title": "Press Secretary",
    "office": "Ohio Democratic Member",
    "location": "D.C./District",
    "posting_date": "2014-11-03",
    "description": "Ohio Democratic Member seeks a hardworking Press Secretary to join a busy and proactive team. Applicant must have previous speech writing experience; thrive at multitasking and working long hours; and, have sound political judgment.\n\nResponsibilities include, but may not be limited to, speech writing, drafting news releases, talking points, and op-eds; responding to press inquiries in a timely and appropriate manner; early daily news clips; monitoring the news/ social media platforms throughout the day; and supervising the development of website and social media content. Duties also include: booking interviews and pitching stories; developing relationships with reporters; organizing events; and developing and implementing media, communications, and public relations strategies. The successful applicant must be a team player, and will work closely with the Chief of Staff, Communications Director, and D.C./ District team.\n\nThis is not an entry-level position. Professional communications and on-the-record experience is required. Hill experience and familiarity with Ohio, especially Northeastern Ohio, is strongly preferred. Candidates should have knowledge of the legislative process, as well as the ability to identify local and national press opportunities. Salary is commensurate with experience. Please send cover letter, resume, and three original writing samples to District11Resumes@mail.house.gov with “PRESS SECRETARY” in the subject line. No walk-ins or phone calls.",
    "responsibilities": [
      "Speech writing",
      "Drafting news releases, talking points, and op-eds",
      "Responding to press inquiries in a timely and appropriate manner",
      "Early daily news clips",
      "Monitoring the news/ social media platforms throughout the day",
      "Supervising the development of website and social media content",
      "Booking interviews and pitching stories",
      "Developing relationships with reporters",
      "Organizing events",
      "Developing and implementing media, communications, and public relations strategies"
    ],
    "qualifications": [
      "Professional communications and on-the-record experience is required",
      "Hill experience and familiarity with Ohio, especially Northeastern Ohio, is strongly preferred",
      "Knowledge of the legislative process",
      "Ability to identify local and national press opportunities"
    ],
    "how_to_apply": "Please send cover letter, resume, and three original writing samples to District11Resumes@mail.house.gov with “PRESS SECRETARY” in the subject line. No walk-ins or phone calls.",
    "salary_info": "Salary is commensurate with experience.",
    "contact": "District11Resumes@mail.house.gov",
    "equal_opportunity": null
  },
  {
    "id": "MEM-346-14",
    "position_title": "Staff Assistant",
    "office": "New Jersey Democrat",
    "location": "Washington, D.C.",
    "posting_date": "2014-11-03",
    "description": "New Jersey Democrat is seeking a highly motivated and organized staff assistant with excellent oral and written communication skills for the Washington, D.C. office. Responsibilities include managing front desk operations, answering telephones, greeting visitors, coordinating tours for visiting guests, processing flag requests, reviewing, sorting, and responding to incoming constituent correspondence, addressing constituent matters, and assisting the Member and legislative staff as needed. Additional duties include management of the website and social media activities, including official Facebook and Twitter accounts.",
    "responsibilities": [
      "Managing front desk operations",
      "Answering telephones",
      "Greeting visitors",
      "Coordinating tours for visiting guests",
      "Processing flag requests",
      "Reviewing, sorting, and responding to incoming constituent correspondence",
      "Addressing constituent matters",
      "Assisting the Member and legislative staff as needed",
      "Management of the website and social media activities, including official Facebook and Twitter accounts"
    ],
    "qualifications": [],
    "how_to_apply": "Please e-mail cover letter, resume and two brief writing samples to nj08jobs@gmail.com. Please no calls or drop-ins.",
    "salary_info": null,
    "contact": "nj08jobs@gmail.com",
    "equal_opportunity": null
  },
  {
    "id": "MEM-340-14",
    "position_title": "Staff Assistant",
    "office": "Virginia Democrat",
    "location": "Capitol Hill",
    "posting_date": "2014-11-03",
    "description": "Virginia Democrat seeks an energetic, self-motivated, and organized Staff Assistant. Applicants should demonstrate strong interpersonal skills, be comfortable with managing multiple tasks, and have experience working on deadline in a high pressure setting.",
    "responsibilities": [
      "staffing the front office and greeting visitors",
      "answering phones",
      "coordinating and executing flag and tour requests",
      "managing office intern program",
      "assisting with mail processing -- reviewing, sorting and responding to constituent mail",
      "tracking legislative issues",
      "assisting with research",
      "coordinating IT services",
      "helping with other projects as needed"
    ],
    "qualifications": [
      "Applicants should have experience interacting with the public, as well as possess strong writing, communication, and organizational skills.",
      "Positive, team-oriented attitude required.",
      "Previous Capitol Hill or internship experience preferred.",
      "Ties to Virginia and bilingual in Spanish a plus."
    ],
    "how_to_apply": "Please submit resume and cover letter to vacongressionalresumes@gmail.com.",
    "salary_info": null,
    "contact": "vacongressionalresumes@gmail.com",
    "equal_opportunity": null
  }
]